mediapro/__init__.py
mediapro-0.0.1.dist-info/METADATA
mediapro-0.0.1.dist-info/WHEEL
mediapro-0.0.1.dist-info/top_level.txt
mediapro-0.0.1.dist-info/RECORD
