Metadata-Version: 2.1
Name: mediapro
Version: 0.0.1
Summary: All about media processing
Home-page: https://github.com/shengbinmeng/mediapro
Author: MediaPro Developers
Author-email: mediapro@shengbin.me
License: UNKNOWN
Platform: UNKNOWN
Classifier: Programming Language :: Python
Classifier: Programming Language :: Python :: 2
Classifier: Programming Language :: Python :: 3
